{
    "The neural basis of cognitive development: A constructivist manifesto": {
        "authors": [
            {
                "author_name": "Steven R. Quartz",
                "url": "/core/search?filters%5BauthorTerms%5D=Steven R. Quartz&eventCode=SE-AU"
            },
            {
                "author_name": "Terrence J. Sejnowski",
                "url": "/core/search?filters%5BauthorTerms%5D=Terrence J. Sejnowski&eventCode=SE-AU"
            }
        ],
        "url": "https://www.cambridge.org/core/journals/behavioral-and-brain-sciences/article/neural-basis-of-cognitive-development-a-constructivist-manifesto/ADDEC5A733C14B2FA9BD635E08EC1234",
        "article_type": "Research Article",
        "references": [],
        "commentaries": [
            {
                "authors": [
                    {
                        "author_name": "Robert A. Barton",
                        "url": "/core/search?filters%5BauthorTerms%5D=Robert A. Barton&eventCode=SE-AU"
                    }
                ],
                "title": "Neural constructivism: How mammals make modules",
                "url": "https://www.cambridge.org/core/journals/behavioral-and-brain-sciences/article/neural-constructivism-how-mammals-make-modules/E40908A4B146B90070AF82DBD3E30D49",
                "article_type": "Open Peer Commentary",
                "references": []
            },
            {
                "authors": [
                    {
                        "author_name": "Derek Bickerton",
                        "url": "/core/search?filters%5BauthorTerms%5D=Derek Bickerton&eventCode=SE-AU"
                    }
                ],
                "title": "Constructivism, nativism, and explanatory adequacy",
                "url": "https://www.cambridge.org/core/journals/behavioral-and-brain-sciences/article/constructivism-nativism-and-explanatory-adequacy/E12EA6CC54EE851C62C035F3E1FDF68D",
                "article_type": "Open Peer Commentary",
                "references": []
            },
            {
                "authors": [
                    {
                        "author_name": "James E. Black",
                        "url": "/core/search?filters%5BauthorTerms%5D=James E. Black&eventCode=SE-AU"
                    },
                    {
                        "author_name": "William T. Greenough",
                        "url": "/core/search?filters%5BauthorTerms%5D=William T. Greenough&eventCode=SE-AU"
                    }
                ],
                "title": "How to build a brain: Multiple memory systems have evolved and only some of them are constructivist",
                "url": "https://www.cambridge.org/core/journals/behavioral-and-brain-sciences/article/how-to-build-a-brain-multiple-memory-systems-have-evolved-and-only-some-of-them-are-constructivist/5716A94AED84F75A8528D6BCA795F8ED",
                "article_type": "Open Peer Commentary",
                "references": []
            },
            {
                "authors": [
                    {
                        "author_name": "Enrico Blanzieri",
                        "url": "/core/search?filters%5BauthorTerms%5D=Enrico Blanzieri&eventCode=SE-AU"
                    }
                ],
                "title": "Dynamical learning algorithms for neural networks and neural constructivism",
                "url": "https://www.cambridge.org/core/journals/behavioral-and-brain-sciences/article/dynamical-learning-algorithms-for-neural-networks-and-neural-constructivism/777501E076A751CEEE44E93D8AA3F21D",
                "article_type": "Open Peer Commentary",
                "references": []
            },
            {
                "authors": [
                    {
                        "author_name": "Johan J. Bolhuis",
                        "url": "/core/search?filters%5BauthorTerms%5D=Johan J. Bolhuis&eventCode=SE-AU"
                    }
                ],
                "title": "Learning, development, and synaptic plasticity: The avian connection",
                "url": "https://www.cambridge.org/core/journals/behavioral-and-brain-sciences/article/learning-development-and-synaptic-plasticity-the-avian-connection/15FB3EA23AB4A02F7EEBD56F00586B72",
                "article_type": "Open Peer Commentary",
                "references": []
            },
            {
                "authors": [
                    {
                        "author_name": "G. Dehaene-Lambertz",
                        "url": "/core/search?filters%5BauthorTerms%5D=G. Dehaene-Lambertz&eventCode=SE-AU"
                    },
                    {
                        "author_name": "Stanislas Dehaene",
                        "url": "/core/search?filters%5BauthorTerms%5D=Stanislas Dehaene&eventCode=SE-AU"
                    }
                ],
                "title": "In defense of learning by selection: Neurobiological and behavioral evidence revisited",
                "url": "https://www.cambridge.org/core/journals/behavioral-and-brain-sciences/article/in-defense-of-learning-by-selection-neurobiological-and-behavioral-evidence-revisited/5963287ABC1B8ED937C8A5EC75F324FC",
                "article_type": "Open Peer Commentary",
                "references": []
            },
            {
                "authors": [
                    {
                        "author_name": "T. Elliott",
                        "url": "/core/search?filters%5BauthorTerms%5D=T. Elliott&eventCode=SE-AU"
                    },
                    {
                        "author_name": "N. R. Shadbolt",
                        "url": "/core/search?filters%5BauthorTerms%5D=N. R. Shadbolt&eventCode=SE-AU"
                    }
                ],
                "title": "Neurotrophic factors, neuronal selectionism, and neuronal proliferation",
                "url": "https://www.cambridge.org/core/journals/behavioral-and-brain-sciences/article/neurotrophic-factors-neuronal-selectionism-and-neuronal-proliferation/6DD266B0C0B607C9A09B2FD61C13876A",
                "article_type": "Open Peer Commentary",
                "references": []
            },
            {
                "authors": [
                    {
                        "author_name": "David Estes",
                        "url": "/core/search?filters%5BauthorTerms%5D=David Estes&eventCode=SE-AU"
                    },
                    {
                        "author_name": "Karen Bartsch",
                        "url": "/core/search?filters%5BauthorTerms%5D=Karen Bartsch&eventCode=SE-AU"
                    }
                ],
                "title": "Constraining the brain: The role of developmental psychology in developmental cognitive neuroscience",
                "url": "https://www.cambridge.org/core/journals/behavioral-and-brain-sciences/article/constraining-the-brain-the-role-of-developmental-psychology-in-developmental-cognitive-neuroscience/7EB384CEB4F543723CC27BEBAAC7687E",
                "article_type": "Open Peer Commentary",
                "references": []
            },
            {
                "authors": [
                    {
                        "author_name": "Jerome A. Feldman",
                        "url": "/core/search?filters%5BauthorTerms%5D=Jerome A. Feldman&eventCode=SE-AU"
                    }
                ],
                "title": "Radical empiricism is not constructive",
                "url": "https://www.cambridge.org/core/journals/behavioral-and-brain-sciences/article/radical-empiricism-is-not-constructive/AD4958A92AF09F997D761D09FD268B5E",
                "article_type": "Open Peer Commentary",
                "references": []
            },
            {
                "authors": [
                    {
                        "author_name": "Barbara L. Finlay",
                        "url": "/core/search?filters%5BauthorTerms%5D=Barbara L. Finlay&eventCode=SE-AU"
                    }
                ],
                "title": "So many problems, so little time: Evolution and the dendrite",
                "url": "https://www.cambridge.org/core/journals/behavioral-and-brain-sciences/article/so-many-problems-so-little-time-evolution-and-the-dendrite/D80F67083F411505102C00960E565DB4",
                "article_type": "Open Peer Commentary",
                "references": []
            },
            {
                "authors": [
                    {
                        "author_name": "Jeffrey Foss",
                        "url": "/core/search?filters%5BauthorTerms%5D=Jeffrey Foss&eventCode=SE-AU"
                    }
                ],
                "title": "Irresistible environment meets immovable neurons",
                "url": "https://www.cambridge.org/core/journals/behavioral-and-brain-sciences/article/irresistible-environment-meets-immovable-neurons/F41CB3B5EE394A873A65C15D57E318C3",
                "article_type": "Open Peer Commentary",
                "references": []
            },
            {
                "authors": [
                    {
                        "author_name": "Stephen Grossberg",
                        "url": "/core/search?filters%5BauthorTerms%5D=Stephen Grossberg&eventCode=SE-AU"
                    }
                ],
                "title": "Neural models of development and learning",
                "url": "https://www.cambridge.org/core/journals/behavioral-and-brain-sciences/article/neural-models-of-development-and-learning/A2D986122AF9C68A11E49E51BC477355",
                "article_type": "Open Peer Commentary",
                "references": []
            },
            {
                "authors": [
                    {
                        "author_name": "Gary Haith",
                        "url": "/core/search?filters%5BauthorTerms%5D=Gary Haith&eventCode=SE-AU"
                    }
                ],
                "title": "Processing limitations can help neural growth build hierarchical representations",
                "url": "https://www.cambridge.org/core/journals/behavioral-and-brain-sciences/article/processing-limitations-can-help-neural-growth-build-hierarchical-representations/82E25F4AE65BFEA5645B72B8673B3B3B",
                "article_type": "Open Peer Commentary",
                "references": []
            },
            {
                "authors": [
                    {
                        "author_name": "James Hurford",
                        "url": "/core/search?filters%5BauthorTerms%5D=James Hurford&eventCode=SE-AU"
                    },
                    {
                        "author_name": "Sam Joseph",
                        "url": "/core/search?filters%5BauthorTerms%5D=Sam Joseph&eventCode=SE-AU"
                    },
                    {
                        "author_name": "Simon Kirby",
                        "url": "/core/search?filters%5BauthorTerms%5D=Simon Kirby&eventCode=SE-AU"
                    },
                    {
                        "author_name": "Alastair Reid",
                        "url": "/core/search?filters%5BauthorTerms%5D=Alastair Reid&eventCode=SE-AU"
                    }
                ],
                "title": "Evolution might select constructivism",
                "url": "https://www.cambridge.org/core/journals/behavioral-and-brain-sciences/article/evolution-might-select-constructivism/2420A7E2F86CC598FEC9F928F5E7800C",
                "article_type": "Open Peer Commentary",
                "references": []
            },
            {
                "authors": [
                    {
                        "author_name": "G. M. Innocenti",
                        "url": "/core/search?filters%5BauthorTerms%5D=G. M. Innocenti&eventCode=SE-AU"
                    }
                ],
                "title": "“Differentiationism” can reconcile selectionism and constructivism",
                "url": "https://www.cambridge.org/core/journals/behavioral-and-brain-sciences/article/differentiationism-can-reconcile-selectionism-and-constructivism/FD9A86523F7D58A7681FE807215559C1",
                "article_type": "Open Peer Commentary",
                "references": []
            },
            {
                "authors": [
                    {
                        "author_name": "Mark H. Johnson",
                        "url": "/core/search?filters%5BauthorTerms%5D=Mark H. Johnson&eventCode=SE-AU"
                    },
                    {
                        "author_name": "Liz Bates",
                        "url": "/core/search?filters%5BauthorTerms%5D=Liz Bates&eventCode=SE-AU"
                    },
                    {
                        "author_name": "Jeff Elman",
                        "url": "/core/search?filters%5BauthorTerms%5D=Jeff Elman&eventCode=SE-AU"
                    },
                    {
                        "author_name": "Annette Karmiloff-Smith",
                        "url": "/core/search?filters%5BauthorTerms%5D=Annette Karmiloff-Smith&eventCode=SE-AU"
                    },
                    {
                        "author_name": "Kim Plunkett",
                        "url": "/core/search?filters%5BauthorTerms%5D=Kim Plunkett&eventCode=SE-AU"
                    }
                ],
                "title": "Constraints on the construction of cognition",
                "url": "https://www.cambridge.org/core/journals/behavioral-and-brain-sciences/article/constraints-on-the-construction-of-cognition/531780E554521171E5790B32B3549C88",
                "article_type": "Open Peer Commentary",
                "references": []
            },
            {
                "authors": [
                    {
                        "author_name": "Henry Kennedy",
                        "url": "/core/search?filters%5BauthorTerms%5D=Henry Kennedy&eventCode=SE-AU"
                    },
                    {
                        "author_name": "Colette Dehay",
                        "url": "/core/search?filters%5BauthorTerms%5D=Colette Dehay&eventCode=SE-AU"
                    }
                ],
                "title": "Cortical development: A progressive and selective mesh, with or without constructivism",
                "url": "https://www.cambridge.org/core/journals/behavioral-and-brain-sciences/article/cortical-development-a-progressive-and-selective-mesh-with-or-without-constructivism/94C28A8A4411F7DA2A6A92CBE7EB4ED2",
                "article_type": "Open Peer Commentary",
                "references": []
            },
            {
                "authors": [
                    {
                        "author_name": "Denis Mareschal",
                        "url": "/core/search?filters%5BauthorTerms%5D=Denis Mareschal&eventCode=SE-AU"
                    },
                    {
                        "author_name": "Thomas R. Shultz",
                        "url": "/core/search?filters%5BauthorTerms%5D=Thomas R. Shultz&eventCode=SE-AU"
                    }
                ],
                "title": "From neural constructivism to children's cognitive development: Bridging the gap",
                "url": "https://www.cambridge.org/core/journals/behavioral-and-brain-sciences/article/from-neural-constructivism-to-childrens-cognitive-development-bridging-the-gap/180250BAB5C230D3FD65AEDB8F7A202E",
                "article_type": "Open Peer Commentary",
                "references": []
            },
            {
                "authors": [
                    {
                        "author_name": "Gin McCollum",
                        "url": "/core/search?filters%5BauthorTerms%5D=Gin McCollum&eventCode=SE-AU"
                    }
                ],
                "title": "More mathematics: Bodily-kinaesthetic intelligence",
                "url": "https://www.cambridge.org/core/journals/behavioral-and-brain-sciences/article/more-mathematics-bodilykinaesthetic-intelligence/4719352E2587D77497F6E6B700C351E9",
                "article_type": "Open Peer Commentary",
                "references": []
            },
            {
                "authors": [
                    {
                        "author_name": "Dale Purves",
                        "url": "/core/search?filters%5BauthorTerms%5D=Dale Purves&eventCode=SE-AU"
                    }
                ],
                "title": "Neural construction: Two and a half cheers for Quartz & Sejnowski!",
                "url": "https://www.cambridge.org/core/journals/behavioral-and-brain-sciences/article/neural-construction-two-and-a-half-cheers-for-quartz-sejnowski/23AAC4F840AC0882D114D1948C1840F0",
                "article_type": "Open Peer Commentary",
                "references": []
            },
            {
                "authors": [
                    {
                        "author_name": "M. E. J. Raijmakers",
                        "url": "/core/search?filters%5BauthorTerms%5D=M. E. J. Raijmakers&eventCode=SE-AU"
                    }
                ],
                "title": "Is the learning paradox resolved?",
                "url": "https://www.cambridge.org/core/journals/behavioral-and-brain-sciences/article/is-the-learning-paradox-resolved/A8125CA097369642E65F32733D29F994",
                "article_type": "Open Peer Commentary",
                "references": []
            },
            {
                "authors": [
                    {
                        "author_name": "George N. Reeke",
                        "url": "/core/search?filters%5BauthorTerms%5D=George N. Reeke&eventCode=SE-AU"
                    }
                ],
                "title": "Constructivism: Can directed mutation improve on classical neural selection?",
                "url": "https://www.cambridge.org/core/journals/behavioral-and-brain-sciences/article/constructivism-can-directed-mutation-improve-on-classical-neural-selection/700D1981A26965A85C4EC9CB7D8EA2DE",
                "article_type": "Open Peer Commentary",
                "references": []
            },
            {
                "authors": [
                    {
                        "author_name": "Arnold B. Scheibel",
                        "url": "/core/search?filters%5BauthorTerms%5D=Arnold B. Scheibel&eventCode=SE-AU"
                    }
                ],
                "title": "The right way, the wrong way, and the army way: A dendritic parable",
                "url": "https://www.cambridge.org/core/journals/behavioral-and-brain-sciences/article/right-way-the-wrong-way-and-the-army-way-a-dendritic-parable/436F122D5ED870D326B0B055DB6DA077",
                "article_type": "Open Peer Commentary",
                "references": []
            },
            {
                "authors": [
                    {
                        "author_name": "Brian J. Scholl",
                        "url": "/core/search?filters%5BauthorTerms%5D=Brian J. Scholl&eventCode=SE-AU"
                    }
                ],
                "title": "Neural constraints on cognitive modularity?",
                "url": "https://www.cambridge.org/core/journals/behavioral-and-brain-sciences/article/neural-constraints-on-cognitive-modularity/B87718D00AA6BCA3C3948F508AAB5A3E",
                "article_type": "Open Peer Commentary",
                "references": []
            },
            {
                "authors": [
                    {
                        "author_name": "Olaf Sporns",
                        "url": "/core/search?filters%5BauthorTerms%5D=Olaf Sporns&eventCode=SE-AU"
                    }
                ],
                "title": "Deconstructing neural constructivism",
                "url": "https://www.cambridge.org/core/journals/behavioral-and-brain-sciences/article/deconstructing-neural-constructivism/E433814C33DDC7C59075FFA669D17AB5",
                "article_type": "Open Peer Commentary",
                "references": []
            },
            {
                "authors": [
                    {
                        "author_name": "George Székely",
                        "url": "/core/search?filters%5BauthorTerms%5D=George Székely&eventCode=SE-AU"
                    }
                ],
                "title": "Learning is remembering",
                "url": "https://www.cambridge.org/core/journals/behavioral-and-brain-sciences/article/learning-is-remembering/C25C0C757B354673B413DD7653D973B8",
                "article_type": "Open Peer Commentary",
                "references": []
            }
        ]
    }
}